cybergear/__init__.py
cybergear/cybergear.py
cybergear_core-0.1.0.dist-info/AUTHORS
cybergear_core-0.1.0.dist-info/METADATA
cybergear_core-0.1.0.dist-info/WHEEL
cybergear_core-0.1.0.dist-info/pbr.json
cybergear_core-0.1.0.dist-info/top_level.txt
cybergear_core-0.1.0.dist-info/RECORD
